clss/__init__.py
clss/config.py
clss/model.py
clss/utils.py
clss_model-0.3.7.dist-info/licenses/LICENSE
clss_model-0.3.7.dist-info/METADATA
clss_model-0.3.7.dist-info/WHEEL
clss_model-0.3.7.dist-info/top_level.txt
clss_model-0.3.7.dist-info/RECORD
