Metadata-Version: 2.4
Name: clss-model
Version: 0.3.7
Summary: Contrastive Learning for Sequence and Structure - co-embeds protein sequences and structures
Author: Guy Yanai, Gabriel Axel, Liam M. Longo, Nir Ben-Tal, Rachel Kolodny
Maintainer-email: Guy Yanai <guy@shay.co.il>
License: MIT
Project-URL: Homepage, https://github.com/guyyanai/CLSS
Project-URL: Repository, https://github.com/guyyanai/CLSS
Project-URL: Bug Tracker, https://github.com/guyyanai/CLSS/issues
Project-URL: Documentation, https://github.com/guyyanai/CLSS
Project-URL: Paper, https://www.biorxiv.org/content/10.1101/2025.09.05.674454v3.full.pdf
Keywords: protein,machine-learning,contrastive-learning,bioinformatics,structure,sequence
Classifier: Development Status :: 3 - Alpha
Classifier: Intended Audience :: Science/Research
Classifier: Topic :: Scientific/Engineering :: Bio-Informatics
Classifier: Topic :: Scientific/Engineering :: Artificial Intelligence
Classifier: Programming Language :: Python :: 3
Classifier: Programming Language :: Python :: 3.8
Classifier: Programming Language :: Python :: 3.9
Classifier: Programming Language :: Python :: 3.10
Classifier: Programming Language :: Python :: 3.11
Classifier: Programming Language :: Python :: 3.12
Classifier: Programming Language :: Python :: 3.13
Requires-Python: >=3.8
License-File: LICENSE
Requires-Dist: torch>=1.11.0
Requires-Dist: pytorch-lightning>=1.6.0
Requires-Dist: transformers>=4.20.0
Requires-Dist: esm>=2.0.0
Requires-Dist: pandas>=1.3.0
Requires-Dist: scikit-learn>=1.0.0
Requires-Dist: wandb>=0.12.0
Requires-Dist: tqdm>=4.62.0
Requires-Dist: huggingface-hub>=0.8.0
Provides-Extra: dev
Requires-Dist: pytest>=6.0; extra == "dev"
Requires-Dist: pytest-cov>=2.10; extra == "dev"
Requires-Dist: black>=22.0; extra == "dev"
Requires-Dist: isort>=5.0; extra == "dev"
Requires-Dist: flake8>=4.0; extra == "dev"
Requires-Dist: mypy>=0.900; extra == "dev"
Requires-Dist: pre-commit>=2.15.0; extra == "dev"
Provides-Extra: notebooks
Requires-Dist: jupyter>=1.0.0; extra == "notebooks"
Requires-Dist: matplotlib>=3.3.0; extra == "notebooks"
Requires-Dist: seaborn>=0.11.0; extra == "notebooks"
Requires-Dist: plotly>=5.0.0; extra == "notebooks"
Requires-Dist: ipywidgets>=7.6.0; extra == "notebooks"
Provides-Extra: docs
Requires-Dist: sphinx>=4.0.0; extra == "docs"
Requires-Dist: sphinx-rtd-theme>=1.0.0; extra == "docs"
Requires-Dist: myst-parser>=0.15.0; extra == "docs"
Dynamic: license-file
